{"promptCode":{"definition":{"$schema":"https://schema.management.azure.com/providers/Microsoft.Logic/schemas/2016-06-01/workflowdefinition.json#","actions":{"HTTP_Request_to_Chrome":{"inputs":{"method":"POST","uri":"https://your-chrome-url.com/api","headers":{"Content-Type":"application/json"},"body":{"sampleKey":"sampleValue"}},"runAfter":{},"type":"Http"}},"triggers":{"manualTrigger":{"inputs":{"schema":{}},"kind":"Http","type":"Request"}},"outputs":{}},"kind":"Stateful","type":"Microsoft.Logic/workflows","location":"[Your Azure Location]","name":"[Your Logic App Name]"},"logicAppDetails":{"name":"promptlogicapp","resourceGroup":"CustomAppsIntServices","subscription":"047ae087-7d35-4c57-8fe9-7a442cc9cf16"}}
