[{"definition":"{\n    \"definition\": {\n        \"$schema\": \"https://schema.management.azure.com/providers/Microsoft.Logic/schemas/2016-06-01/workflowdefinition.json#\",\n        \"actions\": {\n            \"HTTP_to_Chrome\": {\n                \"type\": \"Http\",\n                \"inputs\": {\n                    \"method\": \"POST\",\n                    \"uri\": \"https://api.chrome-automation-service.com/execute\", \n                    \"headers\": {\n                        \"Content-Type\": \"application/json\"\n                    },\n                    \"body\": {\n                        \"command\": \"OPEN_TAB\",\n                        \"url\": \"@triggerBody()['url']\" \n                    }\n                },\n                \"runAfter\": {}\n            }\n        },\n        \"triggers\": {\n            \"manualTrigger\": {\n                \"type\": \"Request\",\n                \"kind\": \"Http\",\n                \"inputs\": {\n                    \"schema\": {\n                        \"type\": \"object\",\n                        \"properties\": {\n                            \"url\": {\n                                \"type\": \"string\"\n                            }\n                        },\n                        \"required\": [\n                            \"url\"\n                        ]\n                    }\n                }\n            }\n        },\n        \"contentVersion\": \"1.0.0.0\"\n    },\n    \"parameters\": {\n        \"$connections\": {\n            \"defaultValue\": {},\n            \"type\": \"Object\"\n        }\n    }\n}","logicAppDetails":{"name":"promptlogicapp","resourceGroup":"CustomAppsIntServices","subscription":"047ae087-7d35-4c57-8fe9-7a442cc9cf16"}}]